serialcables_hydra/__init__.py
serialcables_hydra/cli.py
serialcables_hydra/controller.py
serialcables_hydra/enums.py
serialcables_hydra/models.py
serialcables_hydra/monitor.py
serialcables_hydra-1.3.2.dist-info/licenses/LICENSE
serialcables_hydra-1.3.2.dist-info/METADATA
serialcables_hydra-1.3.2.dist-info/WHEEL
serialcables_hydra-1.3.2.dist-info/entry_points.txt
serialcables_hydra-1.3.2.dist-info/top_level.txt
serialcables_hydra-1.3.2.dist-info/RECORD
