Metadata-Version: 2.4
Name: serialcables-hydra
Version: 1.3.2
Summary: Python library for controlling Serial Cables PCIe Gen6 HYDRA JBOF System
Author-email: Serial Cables Engineering <hydra@serialcables.com>
License-Expression: MIT
Project-URL: Homepage, https://www.serialcables.com/products/hydra
Project-URL: Repository, https://github.com/serialcables/hydra-controller
Project-URL: Issues, https://github.com/serialcables/hydra-controller/issues
Keywords: PCIe,JBOF,NVMe,storage,monitoring,hardware
Classifier: Development Status :: 4 - Beta
Classifier: Intended Audience :: Developers
Classifier: Topic :: System :: Hardware :: Hardware Drivers
Classifier: Programming Language :: Python :: 3
Classifier: Programming Language :: Python :: 3.7
Classifier: Programming Language :: Python :: 3.8
Classifier: Programming Language :: Python :: 3.9
Classifier: Programming Language :: Python :: 3.10
Classifier: Programming Language :: Python :: 3.11
Classifier: Operating System :: OS Independent
Requires-Python: >=3.7
License-File: LICENSE
Requires-Dist: pyserial>=3.5
Provides-Extra: dev
Requires-Dist: pytest>=7.0; extra == "dev"
Requires-Dist: pytest-cov>=4.0; extra == "dev"
Requires-Dist: black>=22.0; extra == "dev"
Requires-Dist: flake8>=5.0; extra == "dev"
Requires-Dist: mypy>=0.990; extra == "dev"
Requires-Dist: types-pyserial>=3.0; extra == "dev"
Requires-Dist: build>=0.9; extra == "dev"
Requires-Dist: twine>=4.0; extra == "dev"
Dynamic: license-file
